apikick/__init__.py
apikick/apikick.py
apikick/channel_data.py
apikick/chat_data.py
apikick/video_data.py
apikick/utils/__init__.py
apikick/utils/validate.py
APIKick-0.0.1.dist-info/LICENSE
APIKick-0.0.1.dist-info/METADATA
APIKick-0.0.1.dist-info/WHEEL
APIKick-0.0.1.dist-info/top_level.txt
APIKick-0.0.1.dist-info/RECORD
