Metadata-Version: 2.1
Name: APIKick
Version: 0.0.1
Summary: Fast and easy to use Kick.com API
Home-page: https://github.com/Sikriet/KickApi
Author: Sikriet
License: MIT
Keywords: kick,api,kickapi
License-File: LICENSE
Requires-Dist: requests
